athina_client/__init__.py
athina_client/api_base_url/__init__.py
athina_client/api_base_url/athina_api_base_url.py
athina_client/constants/__init__.py
athina_client/constants/athina.py
athina_client/constants/messages.py
athina_client/datasets/__init__.py
athina_client/datasets/dataset.py
athina_client/errors/__init__.py
athina_client/errors/exceptions.py
athina_client/keys/__init__.py
athina_client/keys/athina_api_key.py
athina_client/prompt/__init__.py
athina_client/prompt/prompt.py
athina_client/services/__init__.py
athina_client/services/athina_api_service.py
athina_client-0.2.11.dist-info/METADATA
athina_client-0.2.11.dist-info/WHEEL
athina_client-0.2.11.dist-info/RECORD
